pdfwerks/__init__.py
pdfwerks/main.py
pdfwerks/cli/__init__.py
pdfwerks/cli/arg_parse.py
pdfwerks/cli/cli.py
pdfwerks/core/__init__.py
pdfwerks/core/pdf_tools.py
pdfwerks/core/utils.py
pdfwerks/tui/__init__.py
pdfwerks/tui/file_dialogs.py
pdfwerks/tui/tui.py
pdfwerks/tui/components/__init__.py
pdfwerks/tui/components/confirmation_menu.py
pdfwerks/tui/components/progress_bar.py
pdfwerks/tui/components/reorder_menu.py
pdfwerks/tui/components/selection_menu.py
pdfwerks-1.1.0.dist-info/licenses/LICENSE
pdfwerks-1.1.0.dist-info/METADATA
pdfwerks-1.1.0.dist-info/WHEEL
pdfwerks-1.1.0.dist-info/entry_points.txt
pdfwerks-1.1.0.dist-info/top_level.txt
pdfwerks-1.1.0.dist-info/RECORD
