Metadata-Version: 2.4
Name: pdfwerks
Version: 1.1.0
Summary: A lightweight Python toolkit with multiple tools for PDF manipulation
Author-email: Adithya Menon R <adukottan@gmail.com>
License: MIT License
Project-URL: Repository, https://github.com/adithya-menon-r/PDFwerks.git
Project-URL: Documentation, https://adithya-menon-r.github.io/PDFwerks
Keywords: pdfwerks,pdf,pdf-management,toolkit,tui,cli,python
Classifier: Programming Language :: Python :: 3
Classifier: Programming Language :: Python :: 3.10
Classifier: Programming Language :: Python :: 3.11
Classifier: Programming Language :: Python :: 3.12
Classifier: Programming Language :: Python :: 3.13
Classifier: Operating System :: Microsoft :: Windows
Classifier: Operating System :: POSIX :: Linux
Classifier: Operating System :: MacOS
Classifier: Topic :: Software Development :: Libraries :: Python Modules
Requires-Python: >=3.10
License-File: LICENSE
Requires-Dist: pymupdf>=1.25.0
Requires-Dist: pymupdf4llm>=0.0.23
Requires-Dist: pikepdf>=9.8.0
Requires-Dist: pillow>=11.0.0
Requires-Dist: rich>=10.0.0
Requires-Dist: prompt_toolkit>=3.0.0
Requires-Dist: pyperclip>=1.8.0
Provides-Extra: docs
Requires-Dist: mkdocs>=1.5.0; extra == "docs"
Requires-Dist: mkdocs-material>=9.5.0; extra == "docs"
Provides-Extra: test
Requires-Dist: pytest>=8.3.0; extra == "test"
Dynamic: license-file
